[
  {
    "file_path": "data/candidates_cetwar1/cetwar1_1078113.wav",
    "species_name": "Cetti's Warbler",
    "species_code": "cetwar1",
    "source": "xenocanto",
    "source_id": "XC1078113",
    "recordist": "Jo\u00e3o Tom\u00e1s",
    "vocalization_type": "song",
    "duration_ms": 3000,
    "loudness_lufs": -16.0,
    "quality": "A"
  },
  {
    "file_path": "data/candidates_cetwar1/cetwar1_1063918.wav",
    "species_name": "Cetti's Warbler",
    "species_code": "cetwar1",
    "source": "xenocanto",
    "source_id": "XC1063918",
    "recordist": "Pere Josa",
    "vocalization_type": "song",
    "duration_ms": 3000,
    "loudness_lufs": -16.0,
    "quality": "A"
  },
  {
    "file_path": "data/candidates_cetwar1/cetwar1_1059285.wav",
    "species_name": "Cetti's Warbler",
    "species_code": "cetwar1",
    "source": "xenocanto",
    "source_id": "XC1059285",
    "recordist": "Lionel Triboulin",
    "vocalization_type": "song",
    "duration_ms": 3000,
    "loudness_lufs": -16.0,
    "quality": "A"
  },
  {
    "file_path": "data/candidates_cetwar1/cetwar1_1059282.wav",
    "species_name": "Cetti's Warbler",
    "species_code": "cetwar1",
    "source": "xenocanto",
    "source_id": "XC1059282",
    "recordist": "Lionel Triboulin",
    "vocalization_type": "song",
    "duration_ms": 3000,
    "loudness_lufs": -16.0,
    "quality": "A"
  },
  {
    "file_path": "data/candidates_cetwar1/cetwar1_1049043.wav",
    "species_name": "Cetti's Warbler",
    "species_code": "cetwar1",
    "source": "xenocanto",
    "source_id": "XC1049043",
    "recordist": "Jorge Leit\u00e3o",
    "vocalization_type": "song",
    "duration_ms": 3000,
    "loudness_lufs": -16.0,
    "quality": "A"
  },
  {
    "file_path": "data/candidates_cetwar1/cetwar1_1064751.wav",
    "species_name": "Cetti's Warbler",
    "species_code": "cetwar1",
    "source": "xenocanto",
    "source_id": "XC1064751",
    "recordist": "Julien Birard",
    "vocalization_type": "call",
    "duration_ms": 3000,
    "loudness_lufs": -16.0,
    "quality": "A"
  },
  {
    "file_path": "data/candidates_cetwar1/cetwar1_1064567.wav",
    "species_name": "Cetti's Warbler",
    "species_code": "cetwar1",
    "source": "xenocanto",
    "source_id": "XC1064567",
    "recordist": "Clement Bruneau",
    "vocalization_type": "call",
    "duration_ms": 3000,
    "loudness_lufs": -16.0,
    "quality": "A"
  },
  {
    "file_path": "data/candidates_cetwar1/cetwar1_1039475.wav",
    "species_name": "Cetti's Warbler",
    "species_code": "cetwar1",
    "source": "xenocanto",
    "source_id": "XC1039475",
    "recordist": "Esperanza Poveda",
    "vocalization_type": "call",
    "duration_ms": 3000,
    "loudness_lufs": -16.0,
    "quality": "A"
  }
]