[
  {
    "clip_id": "AMCR_180c06d4",
    "species_code": "AMCR",
    "common_name": "American Crow",
    "vocalization_type": "call",
    "duration_ms": 2357,
    "quality_score": 5,
    "source": "xenocanto",
    "source_id": "XC1056042",
    "file_path": "data/clips/AMCR_1056042.wav",
    "spectrogram_path": "data/spectrograms/AMCR_1056042.png"
  },
  {
    "clip_id": "BLJA_824faa3e",
    "species_code": "BLJA",
    "common_name": "Blue Jay",
    "vocalization_type": "song",
    "duration_ms": 3000,
    "quality_score": 5,
    "source": "xenocanto",
    "source_id": "XC1046664",
    "file_path": "data/clips/BLJA_1046664.wav",
    "spectrogram_path": "data/spectrograms/BLJA_1046664.png"
  },
  {
    "clip_id": "CARW_846ffdee",
    "species_code": "CARW",
    "common_name": "Carolina Wren",
    "vocalization_type": "call",
    "duration_ms": 1917,
    "quality_score": 5,
    "source": "xenocanto",
    "source_id": "XC995314",
    "file_path": "data/clips/CARW_995314.wav",
    "spectrogram_path": "data/spectrograms/CARW_995314.png"
  },
  {
    "clip_id": "NOCA_fc10a42a",
    "species_code": "NOCA",
    "common_name": "Northern Cardinal",
    "vocalization_type": "call",
    "duration_ms": 3000,
    "quality_score": 5,
    "source": "xenocanto",
    "source_id": "XC1070756",
    "file_path": "data/clips/NOCA_1070756.wav",
    "spectrogram_path": "data/spectrograms/NOCA_1070756.png"
  },
  {
    "clip_id": "TUTI_b7ca26c5",
    "species_code": "TUTI",
    "common_name": "Tufted Titmouse",
    "vocalization_type": "call",
    "duration_ms": 3000,
    "quality_score": 5,
    "source": "xenocanto",
    "source_id": "XC1035994",
    "file_path": "data/clips/TUTI_1035994.wav",
    "spectrogram_path": "data/spectrograms/TUTI_1035994.png"
  }
]